sql_logfire/__init__.py
sql_logfire/core.py
sql_logfire/dashboard.py
sql_logfire/models.py
sql_logfire/integrations/__init__.py
sql_logfire/integrations/fastapi.py
sql_logfire-0.1.1.dist-info/METADATA
sql_logfire-0.1.1.dist-info/WHEEL
sql_logfire-0.1.1.dist-info/RECORD
