Metadata-Version: 2.4
Name: sql-logfire
Version: 0.1.1
Summary: A drop-in replacement for Graylog using your existing SQL database.
Project-URL: Homepage, https://github.com/Bittu2903/sql-logfire
Project-URL: Repository, https://github.com/Bittu2903/sql-logfire
Project-URL: Issues, https://github.com/Bittu2903/sql-logfire/issues
Author-email: Bittu Singh <bittusinghtech@gmail.com>
Classifier: Framework :: FastAPI
Classifier: License :: OSI Approved :: MIT License
Classifier: Operating System :: OS Independent
Classifier: Programming Language :: Python :: 3
Classifier: Programming Language :: Python :: 3 :: Only
Classifier: Topic :: Database
Classifier: Topic :: System :: Logging
Requires-Python: >=3.8
Requires-Dist: fastapi>=0.95
Requires-Dist: greenlet>=2.0
Requires-Dist: psycopg2-binary>=2.9
Requires-Dist: psycopg>=3.1
Requires-Dist: pydantic>=1.10
Requires-Dist: sqlalchemy<3.0,>=1.4
Requires-Dist: uvicorn[standard]>=0.22
Provides-Extra: dev
Requires-Dist: black; extra == 'dev'
Requires-Dist: mypy; extra == 'dev'
Requires-Dist: pytest>=7.0; extra == 'dev'
Requires-Dist: ruff; extra == 'dev'
Provides-Extra: postgres
Requires-Dist: psycopg2-binary>=2.9; extra == 'postgres'
Requires-Dist: psycopg>=3.1; extra == 'postgres'
Provides-Extra: sqlite
